{
	"users": [
		{
			"id": 12,
			"name": "Ahmed",
			"password": "123"
		}
	],
	"courses": [
		{
			"id": 1,
			"course_name": "Introduction to Computer Science",
			"course_code": "CSE101",
			"grades": {
				"midterm": 20,
				"assignment": 18,
				"attendance": 4,
				"final": 45
			}
		},
		{
			"id": 2,
			"course_name": "English Composition",
			"course_code": "ENG201",
			"grades": {
				"midterm": 22,
				"assignment": 16,
				"attendance": 5,
				"final": 48
			}
		},
		{
			"id": 3,
			"course_name": "Calculus I",
			"course_code": "MATH301",
			"grades": {
				"midterm": 18,
				"assignment": 20,
				"attendance": 3,
				"final": 47
			}
		},
		{
			"id": 4,
			"course_name": "Physics for Engineers",
			"course_code": "PHY401",
			"grades": {
				"midterm": 21,
				"assignment": 19,
				"attendance": 4,
				"final": 46
			}
		},
		{
			"id": 5,
			"course_name": "Organic Chemistry",
			"course_code": "CHEM501",
			"grades": {
				"midterm": 19,
				"assignment": 17,
				"attendance": 4,
				"final": 43
			}
		},
		{
			"id": 6,
			"course_name": "Introduction to Biology",
			"course_code": "BIO601",
			"grades": {
				"midterm": 23,
				"assignment": 20,
				"attendance": 5,
				"final": 49
			}
		},
		{
			"id": 7,
			"course_name": "Artificial Intelligence Fundamentals",
			"course_code": "AI701",
			"grades": {
				"midterm": 24,
				"assignment": 22,
				"attendance": 5,
				"final": 47
			}
		}
	],
	"notifications": [
		{
			"id": 1,
			"title": "Notification 1",
			"message": "This is the first notification",
			"route": "/home"
		},
		{
			"id": 2,
			"title": "Notification 2",
			"message": "This is the second notification",
			"route": "/home"
		}
	]
}